building_plus/__init__.py
building_plus/basic/__init__.py
building_plus/basic/area_weighted_temperature.py
building_plus/basic/eval_curve.py
building_plus/basic/exterior_convection.py
building_plus/basic/file_handling.py
building_plus/basic/interpolate_weather.py
building_plus/basic/leward_calc.py
building_plus/basic/natural_convection.py
building_plus/basic/psychometric.py
building_plus/basic/solar_calc.py
building_plus/basic/solve_surface_temp.py
building_plus/basic/thermostat_humidistat.py
building_plus/basic/two_way_interp.py
building_plus/basic/wind_speed_calc.py
building_plus/basic/window_convection.py
building_plus/basic/window_solar_transmittance.py
building_plus/components/__init__.py
building_plus/components/air_terminals.py
building_plus/components/availability_managers.py
building_plus/components/cooling_coil.py
building_plus/components/cooling_tower.py
building_plus/components/detailed_water_coil.py
building_plus/components/fan_calc.py
building_plus/components/half_loop_tank.py
building_plus/components/manager_override.py
building_plus/components/unitary_heat_cool.py
building_plus/components/unitary_systems.py
building_plus/components/water_coil.py
building_plus/components/water_equipment.py
building_plus/components/water_heater.py
building_plus/config/__init__.py
building_plus/config/building.py
building_plus/config/path_spec.py
building_plus/config/user.py
building_plus/config/weather_file.py
building_plus/demo_files/4A_USA_MD_BALTIMORE_TMY2.epw
building_plus/demo_files/RefBldgFullServiceRestaurantNew2004_v1.4_7.2_4A_USA_MD_BALTIMORE.csv
building_plus/demo_files/RefBldgFullServiceRestaurantNew2004_v1.4_7.2_4A_USA_MD_BALTIMORE.eio
building_plus/demo_files/RefBldgFullServiceRestaurantNew2004_v1.4_7.2_4A_USA_MD_BALTIMORE.idf
building_plus/demo_files/RefBldgLargeOfficeNew2004_v1.4_7.2_4A_USA_MD_BALTIMORE.eio
building_plus/demo_files/RefBldgLargeOfficeNew2004_v1.4_7.2_4A_USA_MD_BALTIMORE.idf
building_plus/plot_sim.py
building_plus/process/__init__.py
building_plus-0.1.10.dist-info/LICENSE
building_plus-0.1.10.dist-info/WHEEL
building_plus-0.1.10.dist-info/METADATA
building_plus-0.1.10.dist-info/RECORD
